suanpan_custom_code/__init__.py
suanpan_custom_code/custom_python_code.py
suanpan_custom_code/packages/__init__.py
suanpan_custom_code/packages/common/__init__.py
suanpan_custom_code/packages/common/auto_sync_inputs.py
suanpan_custom_code/packages/common/type_convert.py
suanpan_custom_code-0.0.2.dist-info/METADATA
suanpan_custom_code-0.0.2.dist-info/WHEEL
suanpan_custom_code-0.0.2.dist-info/entry_points.txt
suanpan_custom_code-0.0.2.dist-info/top_level.txt
suanpan_custom_code-0.0.2.dist-info/RECORD
